fast_plotter/__init__.py
fast_plotter/__main__.py
fast_plotter/interval_from_str.py
fast_plotter/plotting.py
fast_plotter/statistics.py
fast_plotter/utils.py
fast_plotter/version.py
fast_plotter/postproc/__init__.py
fast_plotter/postproc/__main__.py
fast_plotter/postproc/functions.py
fast_plotter/postproc/query_curator.py
fast_plotter/postproc/stages.py
fast_plotter-0.10.4.dist-info/METADATA
fast_plotter-0.10.4.dist-info/WHEEL
fast_plotter-0.10.4.dist-info/entry_points.txt
fast_plotter-0.10.4.dist-info/top_level.txt
fast_plotter-0.10.4.dist-info/RECORD
