Metadata-Version: 2.1
Name: fast-plotter
Version: 0.10.4
Summary: F.A.S.T. plotter package
Home-page: https://github.com/fast-hep/fast-plotter
Author: Ben Krikler
Author-email: fast-hep@cern.ch
License: Apache Software License 2.0
Keywords: fast_plotter
Platform: UNKNOWN
Classifier: Development Status :: 3 - Alpha
Classifier: Intended Audience :: Developers
Classifier: Intended Audience :: Science/Research
Classifier: License :: OSI Approved :: Apache Software License
Classifier: Natural Language :: English
Classifier: Programming Language :: Python :: 3
Classifier: Programming Language :: Python :: 3.5
Classifier: Programming Language :: Python :: 3.6
Classifier: Programming Language :: Python :: 3.7
Classifier: Programming Language :: Python :: 3.8
Requires-Dist: matplotlib
Requires-Dist: pandas (>=1.0.0)
Requires-Dist: numpy (>=1.16.5)
Requires-Dist: scipy
Requires-Dist: fast-curator
Requires-Dist: fast-flow
